teleclient/__init__.py
teleclient/client.py
teleclient/tdjson.py
teleclient/text.py
teleclient/utils.py
teleclient/worker.py
teleclient/lib/darwin/libtdjson.dylib
teleclient/lib/linux/libtdjson.so
python_telegram_client-0.17.0.post0.dist-info/LICENSE
python_telegram_client-0.17.0.post0.dist-info/METADATA
python_telegram_client-0.17.0.post0.dist-info/WHEEL
python_telegram_client-0.17.0.post0.dist-info/top_level.txt
python_telegram_client-0.17.0.post0.dist-info/RECORD
