Metadata-Version: 2.1
Name: python-telegram-client
Version: 0.17.0.post0
Summary: Python library to help you build your own Telegram clients
Home-page: https://github.com/jackzzs/python-telegram-client
Author: Alexander Akhmetov
Author-email: me@aleks.sh
License-File: LICENSE
Requires-Dist: telegram-text (~=0.1)
